simple_cpf/__init__.py
simple_cpf/simple_cpf.py
simple_cpf-0.1.4.dist-info/WHEEL
simple_cpf-0.1.4.dist-info/METADATA
simple_cpf-0.1.4.dist-info/entry_points.txt
simple_cpf-0.1.4.dist-info/RECORD
